<GeoServerTileLayer>
  <id>LayerInfoImpl--486c3543:19e618c610c:-7ef7</id>
  <enabled>true</enabled>
  <name>helsinki:parcel_fos_mat</name>
  <mimeFormats>
    <string>image/png</string>
    <string>image/jpeg</string>
  </mimeFormats>
  <gridSubsets>
    <gridSubset>
      <gridSetName>EPSG:4326</gridSetName>
      <extent>
        <coords>
          <double>24.884357452392578</double>
          <double>60.081756591796875</double>
          <double>25.008792877197266</double>
          <double>60.197383880615234</double>
        </coords>
      </extent>
    </gridSubset>
    <gridSubset>
      <gridSetName>EPSG:900913</gridSetName>
      <extent>
        <coords>
          <double>2770114.000318144</double>
          <double>8417962.630862752</double>
          <double>2783966.0884440467</double>
          <double>8443814.95646664</double>
        </coords>
      </extent>
    </gridSubset>
  </gridSubsets>
  <metaWidthHeight>
    <int>4</int>
    <int>4</int>
  </metaWidthHeight>
  <expireCache>0</expireCache>
  <expireClients>0</expireClients>
  <parameterFilters>
    <styleParameterFilter>
      <key>STYLES</key>
      <defaultValue></defaultValue>
      <availableStyles class="sorted-set"/>
      <defaultStyle>helsinki:parcel_fos_clean</defaultStyle>
    </styleParameterFilter>
  </parameterFilters>
  <gutter>0</gutter>
  <cacheWarningSkips/>
</GeoServerTileLayer>